letterboxdpy_test/__init__.py
letterboxdpy_test/list.py
letterboxdpy_test/members.py
letterboxdpy_test/movie.py
letterboxdpy_test/user.py
letterboxdpy_test-1.0.3.dist-info/LICENSE
letterboxdpy_test-1.0.3.dist-info/METADATA
letterboxdpy_test-1.0.3.dist-info/WHEEL
letterboxdpy_test-1.0.3.dist-info/top_level.txt
letterboxdpy_test-1.0.3.dist-info/RECORD
