Metadata-Version: 2.1
Name: letterboxdpy-test
Version: 1.0.3
License-File: LICENSE
